print9/__init__.py
print9/main.py
print9-0.1.6.dist-info/licenses/LICENSE
print9-0.1.6.dist-info/METADATA
print9-0.1.6.dist-info/WHEEL
print9-0.1.6.dist-info/top_level.txt
print9-0.1.6.dist-info/RECORD
