Metadata-Version: 2.4
Name: print9
Version: 0.1.6
Summary: A short description of print9
Home-page: https://github.com/vincentdeneuf/print9
Author: Vincent de Neuf
Author-email: 0189vn@gmail.com
License: MIT
Classifier: Programming Language :: Python :: 3
Classifier: License :: OSI Approved :: MIT License
Classifier: Operating System :: OS Independent
Requires-Python: >=3.6
License-File: LICENSE
Dynamic: license-file
